{"data":{"allFile":{"edges":[{"node":{"relativePath":"gatsby-icon.png","prettySize":"21.2 kB","extension":"png","birthTime":"2 hours ago"}},{"node":{"relativePath":"repeating-pattern.svg","prettySize":"4.51 kB","extension":"svg","birthTime":"16 hours ago"}},{"node":{"relativePath":"gatsby-astronaut.png","prettySize":"167 kB","extension":"png","birthTime":"2 hours ago"}},{"node":{"relativePath":"components/image.js","prettySize":"1.01 kB","extension":"js","birthTime":"2 hours ago"}},{"node":{"relativePath":"components/header.js","prettySize":"763 B","extension":"js","birthTime":"2 hours ago"}},{"node":{"relativePath":"components/layout.js","prettySize":"982 B","extension":"js","birthTime":"2 hours ago"}},{"node":{"relativePath":"components/repeating-pattern.css","prettySize":"317 B","extension":"css","birthTime":"16 hours ago"}},{"node":{"relativePath":"components/seo.js","prettySize":"2.34 kB","extension":"js","birthTime":"2 hours ago"}},{"node":{"relativePath":"pages/404.js","prettySize":"332 B","extension":"js","birthTime":"2 hours ago"}},{"node":{"relativePath":"pages/index.js","prettySize":"693 B","extension":"js","birthTime":"2 hours ago"}},{"node":{"relativePath":"pages/myFiles.js","prettySize":"1.09 kB","extension":"js","birthTime":"2 days ago"}},{"node":{"relativePath":"pages/shop.js","prettySize":"1.02 kB","extension":"js","birthTime":"2 hours ago"}},{"node":{"relativePath":"templates/productTemplate.js","prettySize":"1.79 kB","extension":"js","birthTime":"2 days ago"}},{"node":{"relativePath":"theme/globalStyle.js","prettySize":"5.8 kB","extension":"js","birthTime":"an hour ago"}},{"node":{"relativePath":"pages/faqs.js","prettySize":"365 B","extension":"js","birthTime":"5 minutes ago"}},{"node":{"relativePath":"pages/newarrivals.js","prettySize":"0 B","extension":"js","birthTime":"a few seconds ago"}}]}},"pageContext":{}}